[
null,
{"id":1,"list":[{"code":122,"indent":0,"parameters":[20,20,0,2,1,22]},{"code":111,"indent":0,"parameters":[1,20,0,1,0]},{"code":356,"indent":1,"parameters":["SetGameOverImage game_over_1"]},{"code":0,"indent":1,"parameters":[]},{"code":412,"indent":0,"parameters":[]},{"code":111,"indent":0,"parameters":[1,20,0,2,0]},{"code":356,"indent":1,"parameters":["SetGameOverImage game_over_2"]},{"code":0,"indent":1,"parameters":[]},{"code":412,"indent":0,"parameters":[]},{"code":111,"indent":0,"parameters":[1,20,0,3,0]},{"code":356,"indent":1,"parameters":["SetGameOverImage game_over_3"]},{"code":0,"indent":1,"parameters":[]},{"code":412,"indent":0,"parameters":[]},{"code":111,"indent":0,"parameters":[1,20,0,4,0]},{"code":356,"indent":1,"parameters":["SetGameOverImage game_over_4"]},{"code":0,"indent":1,"parameters":[]},{"code":412,"indent":0,"parameters":[]},{"code":111,"indent":0,"parameters":[1,20,0,5,0]},{"code":356,"indent":1,"parameters":["SetGameOverImage game_over_5"]},{"code":0,"indent":1,"parameters":[]},{"code":412,"indent":0,"parameters":[]},{"code":111,"indent":0,"parameters":[1,20,0,6,0]},{"code":356,"indent":1,"parameters":["SetGameOverImage game_over_6"]},{"code":0,"indent":1,"parameters":[]},{"code":412,"indent":0,"parameters":[]},{"code":111,"indent":0,"parameters":[1,20,0,7,0]},{"code":356,"indent":1,"parameters":["SetGameOverImage game_over_7"]},{"code":0,"indent":1,"parameters":[]},{"code":412,"indent":0,"parameters":[]},{"code":111,"indent":0,"parameters":[1,20,0,8,0]},{"code":356,"indent":1,"parameters":["SetGameOverImage game_over_8"]},{"code":0,"indent":1,"parameters":[]},{"code":412,"indent":0,"parameters":[]},{"code":111,"indent":0,"parameters":[1,20,0,9,0]},{"code":356,"indent":1,"parameters":["SetGameOverImage game_over_9"]},{"code":0,"indent":1,"parameters":[]},{"code":412,"indent":0,"parameters":[]},{"code":111,"indent":0,"parameters":[1,20,0,10,0]},{"code":356,"indent":1,"parameters":["SetGameOverImage game_over_10"]},{"code":0,"indent":1,"parameters":[]},{"code":412,"indent":0,"parameters":[]},{"code":111,"indent":0,"parameters":[1,20,0,11,0]},{"code":356,"indent":1,"parameters":["SetGameOverImage game_over_11"]},{"code":0,"indent":1,"parameters":[]},{"code":412,"indent":0,"parameters":[]},{"code":111,"indent":0,"parameters":[1,20,0,12,0]},{"code":356,"indent":1,"parameters":["SetGameOverImage game_over_12"]},{"code":0,"indent":1,"parameters":[]},{"code":412,"indent":0,"parameters":[]},{"code":111,"indent":0,"parameters":[1,20,0,13,0]},{"code":356,"indent":1,"parameters":["SetGameOverImage game_over_13"]},{"code":0,"indent":1,"parameters":[]},{"code":412,"indent":0,"parameters":[]},{"code":111,"indent":0,"parameters":[1,20,0,14,0]},{"code":356,"indent":1,"parameters":["SetGameOverImage game_over_14"]},{"code":0,"indent":1,"parameters":[]},{"code":412,"indent":0,"parameters":[]},{"code":111,"indent":0,"parameters":[1,20,0,15,0]},{"code":356,"indent":1,"parameters":["SetGameOverImage game_over_15"]},{"code":0,"indent":1,"parameters":[]},{"code":412,"indent":0,"parameters":[]},{"code":111,"indent":0,"parameters":[1,20,0,16,0]},{"code":356,"indent":1,"parameters":["SetGameOverImage game_over_16"]},{"code":0,"indent":1,"parameters":[]},{"code":412,"indent":0,"parameters":[]},{"code":111,"indent":0,"parameters":[1,20,0,17,0]},{"code":356,"indent":1,"parameters":["SetGameOverImage game_over_17"]},{"code":0,"indent":1,"parameters":[]},{"code":412,"indent":0,"parameters":[]},{"code":111,"indent":0,"parameters":[1,20,0,18,0]},{"code":356,"indent":1,"parameters":["SetGameOverImage game_over_18"]},{"code":0,"indent":1,"parameters":[]},{"code":412,"indent":0,"parameters":[]},{"code":111,"indent":0,"parameters":[1,20,0,19,0]},{"code":356,"indent":1,"parameters":["SetGameOverImage game_over_19"]},{"code":0,"indent":1,"parameters":[]},{"code":412,"indent":0,"parameters":[]},{"code":111,"indent":0,"parameters":[1,20,0,20,0]},{"code":356,"indent":1,"parameters":["SetGameOverImage game_over_20"]},{"code":0,"indent":1,"parameters":[]},{"code":412,"indent":0,"parameters":[]},{"code":111,"indent":0,"parameters":[1,20,0,21,0]},{"code":356,"indent":1,"parameters":["SetGameOverImage game_over_21"]},{"code":0,"indent":1,"parameters":[]},{"code":412,"indent":0,"parameters":[]},{"code":111,"indent":0,"parameters":[1,20,0,22,0]},{"code":356,"indent":1,"parameters":["SetGameOverImage game_over_22"]},{"code":0,"indent":1,"parameters":[]},{"code":412,"indent":0,"parameters":[]},{"code":0,"indent":0,"parameters":[]}],"name":"GameOverScreen","switchId":1,"trigger":0},
{"id":2,"list":[{"code":122,"indent":0,"parameters":[20,20,0,2,1,9]},{"code":111,"indent":0,"parameters":[1,20,0,1,0]},{"code":250,"indent":1,"parameters":[{"name":"Death - Crunch 1","volume":90,"pitch":100,"pan":0}]},{"code":0,"indent":1,"parameters":[]},{"code":412,"indent":0,"parameters":[]},{"code":111,"indent":0,"parameters":[1,20,0,2,0]},{"code":250,"indent":1,"parameters":[{"name":"Death - Crunch 2","volume":90,"pitch":100,"pan":0}]},{"code":0,"indent":1,"parameters":[]},{"code":412,"indent":0,"parameters":[]},{"code":111,"indent":0,"parameters":[1,20,0,3,0]},{"code":250,"indent":1,"parameters":[{"name":"Death - Crunch 3","volume":90,"pitch":100,"pan":0}]},{"code":0,"indent":1,"parameters":[]},{"code":412,"indent":0,"parameters":[]},{"code":111,"indent":0,"parameters":[1,20,0,4,0]},{"code":250,"indent":1,"parameters":[{"name":"Death - Crush 1","volume":90,"pitch":100,"pan":0}]},{"code":0,"indent":1,"parameters":[]},{"code":412,"indent":0,"parameters":[]},{"code":111,"indent":0,"parameters":[1,20,0,5,0]},{"code":250,"indent":1,"parameters":[{"name":"Death - Crush 2","volume":90,"pitch":100,"pan":0}]},{"code":0,"indent":1,"parameters":[]},{"code":412,"indent":0,"parameters":[]},{"code":111,"indent":0,"parameters":[1,20,0,6,0]},{"code":250,"indent":1,"parameters":[{"name":"Death - Crush 3","volume":90,"pitch":100,"pan":0}]},{"code":0,"indent":1,"parameters":[]},{"code":412,"indent":0,"parameters":[]},{"code":111,"indent":0,"parameters":[1,20,0,7,0]},{"code":250,"indent":1,"parameters":[{"name":"Death - Squerch 1","volume":90,"pitch":100,"pan":0}]},{"code":0,"indent":1,"parameters":[]},{"code":412,"indent":0,"parameters":[]},{"code":111,"indent":0,"parameters":[1,20,0,8,0]},{"code":250,"indent":1,"parameters":[{"name":"Death - Squerch 2","volume":90,"pitch":100,"pan":0}]},{"code":0,"indent":1,"parameters":[]},{"code":412,"indent":0,"parameters":[]},{"code":111,"indent":0,"parameters":[1,20,0,9,0]},{"code":250,"indent":1,"parameters":[{"name":"Death - Squerch 3","volume":90,"pitch":100,"pan":0}]},{"code":0,"indent":1,"parameters":[]},{"code":412,"indent":0,"parameters":[]},{"code":0,"indent":0,"parameters":[]}],"name":"RandomDeathSound","switchId":1,"trigger":0},
{"id":3,"list":[{"code":122,"indent":0,"parameters":[20,20,0,2,1,9]},{"code":111,"indent":0,"parameters":[1,20,0,1,0]},{"code":250,"indent":1,"parameters":[{"name":"Floor Creak 1","volume":90,"pitch":100,"pan":0}]},{"code":0,"indent":1,"parameters":[]},{"code":412,"indent":0,"parameters":[]},{"code":111,"indent":0,"parameters":[1,20,0,2,0]},{"code":250,"indent":1,"parameters":[{"name":"Floor Creak 2","volume":90,"pitch":100,"pan":0}]},{"code":0,"indent":1,"parameters":[]},{"code":412,"indent":0,"parameters":[]},{"code":111,"indent":0,"parameters":[1,20,0,3,0]},{"code":250,"indent":1,"parameters":[{"name":"Floor Creak 3","volume":90,"pitch":100,"pan":0}]},{"code":0,"indent":1,"parameters":[]},{"code":412,"indent":0,"parameters":[]},{"code":111,"indent":0,"parameters":[1,20,0,4,0]},{"code":250,"indent":1,"parameters":[{"name":"Floor Creak 4","volume":90,"pitch":100,"pan":0}]},{"code":0,"indent":1,"parameters":[]},{"code":412,"indent":0,"parameters":[]},{"code":111,"indent":0,"parameters":[1,20,0,5,0]},{"code":250,"indent":1,"parameters":[{"name":"Floor Creak 5","volume":90,"pitch":100,"pan":0}]},{"code":0,"indent":1,"parameters":[]},{"code":412,"indent":0,"parameters":[]},{"code":111,"indent":0,"parameters":[1,20,0,6,0]},{"code":250,"indent":1,"parameters":[{"name":"Floor Creak 6","volume":90,"pitch":100,"pan":0}]},{"code":0,"indent":1,"parameters":[]},{"code":412,"indent":0,"parameters":[]},{"code":111,"indent":0,"parameters":[1,20,0,7,0]},{"code":0,"indent":1,"parameters":[]},{"code":412,"indent":0,"parameters":[]},{"code":111,"indent":0,"parameters":[1,20,0,8,0]},{"code":0,"indent":1,"parameters":[]},{"code":412,"indent":0,"parameters":[]},{"code":111,"indent":0,"parameters":[1,20,0,9,0]},{"code":0,"indent":1,"parameters":[]},{"code":412,"indent":0,"parameters":[]},{"code":0,"indent":0,"parameters":[]}],"name":"RandomFloorCreak","switchId":1,"trigger":0},
{"id":4,"list":[{"code":0,"indent":0,"parameters":[]}],"name":"","switchId":1,"trigger":0}
]